[{"name":"j-graspish-syntax","description":"Atom syntax theme inspired by jGRASP default colors (slightly modified).","version":"1.0.2","downloads":81,"stars":0,"theme":"syntax"},{"name":"j-sheridans_dark_syntax_theme","description":"A classic modern dark theme incorporating lime, sky blue, light red, and purple","version":"0.1.0","downloads":363,"stars":1,"theme":"syntax"},{"name":"jack-compile","description":"Run a Jack source file.","version":"0.1.0","downloads":392,"stars":1},{"name":"jack-n-coke","description":"A snippet boost for Bourbon.io & Neat.bourbon.io users","version":"0.4.0","downloads":338,"stars":6},{"name":"jackhammer-syntax","description":"Dark and Bright Syntax Theme","version":"1.1.0","downloads":65457,"stars":39,"theme":"syntax"},{"name":"jackie-brown-syntax","description":"A color theme based off of the Jackie Brown iTerm theme by Unkulunkulu. A dark brown theme with a 70's color vibe.","version":"0.4.2","downloads":546,"stars":0,"theme":"syntax"},{"name":"jackpot-sensasional-dari-daftar-12-link-situs-judi-slot-online-terpercaya-gacor-2022","downloads":0,"stars":0},{"name":"jackpot-slot","description":"Trik Main Kumpulan Game Gacor Jackpot Slot Bisa Kirim Chip","version":"2.0.0","downloads":0,"stars":0},{"name":"jade","description":"Jade/Pug snippets for Atom","version":"1.2.0","downloads":18997,"stars":11},{"name":"jade-autocompile","description":"Jade autocompiler for Atom.io","version":"0.8.5","downloads":15403,"stars":16},{"name":"jade-beautify","description":"Simple Jade Beautify","version":"0.1.5","downloads":44598,"stars":35},{"name":"jade-bootstrap3-snippets","description":"Bootstrap3 Jade Snippets for Atom","version":"0.3.0","downloads":2726,"stars":2},{"name":"jade-dragon-syntax","description":"Smooth Jade dragon theme.","version":"0.2.0","downloads":278,"stars":2,"theme":"syntax"},{"name":"jade-snippets","description":"Jade Snippets for Atom editor.","version":"0.5.0","downloads":1607,"stars":6},{"name":"jadwal-slot-gacor","description":"Cara Main Jadwal Slot Gacor Terbukti Membayar","version":"2.0.0","downloads":0,"stars":0},{"name":"jaggeryjs-snippets","description":"JaggeryJS Snippets for Atom","version":"1.0.0","downloads":180,"stars":0},{"name":"jajaran-situs-slot-deposit-ovo-terbaik-deposit-10rb-atau-10000","description":"Link Situs Agen Judi Slot Online Via OVO Terbaik Tanpa Potongan Minimal Deposit 10000 atau 10rb","version":"1.2.0","downloads":0,"stars":0},{"name":"jake","description":"Run Jakefile tasks from Atom. Syntax highlighting included.","version":"0.1.6","downloads":212,"stars":0},{"name":"jake-bar","description":"Replace your touchbar with Jake the dog! Get him whenever you want!","version":"2.0.0","downloads":60,"stars":0},{"name":"jam-gacor-slot","description":"Dapatkan Informasi Gacor Situs Terbaru Jam Gacor Slot Tanpa Rekening","version":"2.0.0","downloads":0,"stars":0},{"name":"jam-rtp-slot","description":"Dapatkan Informasi Gacor Dapatkan Informasi Gacor Jam Rtp Slot Online Terbaru","version":"2.0.0","downloads":0,"stars":0},{"name":"jancikuran","downloads":0,"stars":0},{"name":"jancikurang","downloads":0,"stars":0},{"name":"jans-comment-folder","description":"Automatically fold comments in your files","version":"0.1.0","downloads":203,"stars":0},{"name":"japan-colors-syntax","description":"Color theme based on The Traditional Colors of Japan","version":"0.1.1","downloads":2574,"stars":2,"theme":"syntax"},{"name":"japan-util","description":"utilities for Japanese","version":"0.3.0","downloads":16731,"stars":47},{"name":"japanese-contract-md","version":"1.0.0","downloads":2475,"stars":1,"theme":"syntax"},{"name":"japanese-contract-md-syntax","downloads":0,"stars":0},{"name":"japanese-dictionary","version":"0.2.2","downloads":9672,"stars":12},{"name":"japanese-document-md","version":"0.1.2","downloads":855,"stars":0,"theme":"syntax"},{"name":"japanese-menu","description":"メニューバーとコンテキストメニュー、設定画面を日本語化します。","version":"1.15.0","downloads":1938664,"stars":653},{"name":"japanese-non-word-characters","description":"Japanese Non Word Characters","version":"0.1.2","downloads":4167,"stars":2},{"name":"japanese-ten-maru-converter","description":"[、。] and [，．] convert mutually","version":"0.2.2","downloads":4241,"stars":2},{"name":"japanese-word-selection","description":"Japanize word boundary.","version":"0.5.1","downloads":22675,"stars":46},{"name":"japanese-wrap","description":"Word wrap for Japanese text for versions earlier than 1.2.0","version":"0.2.11","downloads":164690,"stars":367},{"name":"japanesque-syntax","version":"0.0.2","downloads":630,"stars":1,"theme":"syntax"},{"name":"jarle-active-editor-info","description":"A simple plugin created using a flight manual tutorial","version":"0.1.2","downloads":116,"stars":0},{"name":"jasmine","description":"Jasmine Snippet   >> JavaScript Unit testing >>  by @code4mk","version":"0.2.1","downloads":588,"stars":0},{"name":"jasmine-runner","description":"Run Jasmine specs from within Atom","version":"0.1.7","downloads":2307,"stars":4},{"name":"jasmine-snippets","description":"Jasmine snippets for Atom (https://atom.io/).","version":"0.1.1","downloads":165,"stars":1},{"name":"java-bytecode-disassembler","description":"Easily disassemble your java bytecode with the OPAL Java Bytecode Disassembler for a one-to-one representation of the class file.","version":"0.13.0","downloads":3493,"stars":0},{"name":"java-class-complete","description":"Java add-on for class-complete","version":"0.0.6","downloads":16989,"stars":2},{"name":"java-classpath-registry","description":"Java Classpath Registry","version":"0.4.0","downloads":57305,"stars":7},{"name":"java-coding-shortcuts","downloads":0,"stars":1},{"name":"java-generator","description":"Generates getter, setter, toString, constructor, and builder methods for java classes.","version":"2.2.3","downloads":46484,"stars":22},{"name":"java-generator-plus","description":"Generates getter, setter, toString, constructor, and builder methods for java classes.","version":"2.6.0","downloads":5220,"stars":1},{"name":"java-import-wiz","description":"Helper for java file imports","version":"0.5.0","downloads":58833,"stars":7},{"name":"java-importer","description":"Helps java users to easily import and organize their import statements","version":"1.4.1","downloads":47864,"stars":19},{"name":"java-plus","description":"Make your Java development experience bareable.","version":"0.1.0","downloads":55809,"stars":22},{"name":"java-snippets","downloads":0,"stars":0},{"name":"javafetch","description":"Java code snippet.","version":"0.3.0","downloads":893,"stars":0},{"name":"javascript-drag-import","description":"Auto import by dragging files from tree-view to your active pane without typing. Supported file types are: JS , JSX , TS , TSX , CSS , SCSS , SASS and LESS.","version":"0.1.13","downloads":25158,"stars":2},{"name":"javascript-importer","description":"Inserts import statements in the beginning of file without moving the cursor.","version":"0.1.0","downloads":1175,"stars":0},{"name":"javascript-object-snippets","description":"JavaScript Object Snippets for Atom editor.","version":"0.3.0","downloads":3510,"stars":3},{"name":"javascript-refactor","description":"JavaScript refactoring support for Atom","version":"0.7.1","downloads":13900,"stars":12},{"name":"javascript-refactoring","downloads":0,"stars":0},{"name":"javascript-regex","description":"Syntax highlighting for JavaScript regular expressions","version":"2.0.13","downloads":26464,"stars":1},{"name":"javascript-snippets","description":"JavaScript & NodeJS Snippets for Atom","version":"1.2.1","downloads":327327,"stars":419},{"name":"javascript-standard-snippets","description":"JavaScript Standard Style Snippets for Atom","version":"0.2.1","downloads":6159,"stars":6},{"name":"javascript-without-snippets","description":"language-javascript without snippets, letting you easily add your own","version":"0.1.2","downloads":720,"stars":0},{"name":"javyus-x","description":"Minimalist syntax theme, created for Java","version":"3.0.0","downloads":1068,"stars":0,"theme":"syntax"},{"name":"jb-syntax","description":"This is my custom syntax theme based on One Dark","version":"0.2.0","downloads":785,"stars":1,"theme":"syntax"},{"name":"jbehave-stepper","description":"Automatically changes your cursor from your JBehave story to the matching Java code","version":"1.2.0","downloads":55,"stars":0},{"name":"jc-nest","description":"develop jd atom design package test","version":"0.2.0","downloads":31,"stars":0},{"name":"jean-louis-usable-light-syntax","description":"A usable light syntax theme for Atom","version":"0.1.3","downloads":94,"stars":0,"theme":"syntax"},{"name":"jean-louis-usable-light-ui","description":"A usable light UI theme for Atom","version":"0.2.1","downloads":170,"stars":0,"theme":"ui"},{"name":"jedi-python","downloads":0,"stars":0},{"name":"jedit-syntax","description":"Jedit Syntax Theme","version":"0.3.11","downloads":552,"stars":0,"theme":"syntax"},{"name":"jedit-white-syntax","version":"0.11.0","downloads":261,"stars":0,"theme":"syntax"},{"name":"jeff5-syntax","description":"My own favorite theme","version":"0.1.0","downloads":31,"stars":0,"theme":"syntax"},{"name":"jekyll","description":"A collection of snippets and tools for Jekyll","version":"2.1.0","downloads":27779,"stars":69},{"name":"jekyll-snippets","description":"Jekyll snippets for the Atom editor","version":"0.3.2","downloads":2445,"stars":6},{"name":"jekyll-syntax-highlighting","description":"Adds syntax highlighting for Jekyll code blocks.","version":"0.1.0","downloads":4854,"stars":5},{"name":"jellybeans","description":"Jellybeans.vim like syntax theme","version":"1.5.0","downloads":4054,"stars":11,"theme":"syntax"},{"name":"jellybeans-syntax","description":"A copy of nanotech's vim jellybeans color theme","version":"0.7.0","downloads":1842,"stars":3,"theme":"syntax"},{"name":"jellyfish-dark-syntax","description":"A very dark, very blue syntax theme.","version":"0.0.18","downloads":240,"stars":1,"theme":"syntax"},{"name":"jellyfish-dark-ui","description":"A dark, blue UI theme.","version":"0.0.7","downloads":233,"stars":0,"theme":"ui"},{"name":"jenkins","description":"Show jenkins build status in atom","version":"0.3.5","downloads":5888,"stars":9},{"name":"jensaarai","description":"Jensaarai collaborative live-coding package for glsl, tidal, and touchdesigner.","version":"0.2.7","downloads":72,"stars":0},{"name":"jeremy-syntax","description":"Green syntax theme","version":"2.2.0","downloads":83,"stars":2,"theme":"syntax"},{"name":"jerry-syntax","description":"Jerry is a very simple boy.","version":"0.2.2","downloads":145,"stars":1,"theme":"syntax"},{"name":"jest-test-toggler","description":"Toggle between jest tests and test subject files.","version":"1.1.0","downloads":179,"stars":0},{"name":"jesus-case","description":"WRiTE LiKE PHiLLY JESUS","version":"1.1.1","downloads":81,"stars":0},{"name":"jextious-syntax","description":"A colorful yet readable theme based on the primary colors.","version":"0.5.0","downloads":2625,"stars":2,"theme":"syntax"},{"name":"jf-fuzzy-finder","description":"Open an editor to a file in the project with `cmd-t`.","version":"1.8.0","downloads":76,"stars":0},{"name":"jfs-ascii-art","description":"The ascii art package from the Atom Flight Manual.","version":"0.1.0","downloads":77,"stars":0},{"name":"jfs-word-count","version":"0.1.0","downloads":53,"stars":0},{"name":"jgrip","description":"A helper tool for react unit testing.","version":"1.0.1","downloads":60,"stars":0},{"name":"jibo-sdk","description":"Jibo SDK","version":"1.7.4","downloads":3912,"stars":6},{"name":"jiosaavn","description":"Listen online/offline music while you code","version":"2.0.0","downloads":54,"stars":0},{"name":"jira-issue-search","description":"Search for Jira issues","version":"1.0.3","downloads":2106,"stars":1},{"name":"jira-timesheet","description":"Send you worktime in timesheet","version":"0.2.0","downloads":353,"stars":0},{"name":"jist","description":"A package to upload snippets or files to GitHub's Gist","version":"0.1.0","downloads":208,"stars":1},{"name":"jk-elegant","description":"support more elegant implements","version":"1.2.2","downloads":259,"stars":1},{"name":"joe-keybinds","description":"Adds joe-style wordstar-like text editing","version":"1.0.0","downloads":329,"stars":0},{"name":"joehannes-steampunk-ui","description":"a geekish steampunk influenced ui theme with darkish styles","version":"0.2.11","downloads":994,"stars":0,"theme":"ui"},{"name":"johns-work-arounds","description":"Provides bundled coding fonts and works around issues in Atom","version":"0.35.0","downloads":840,"stars":1},{"name":"join-lines-smarter","description":"A smarter, language-agnostic Join Lines command.","version":"2.0.1","downloads":375,"stars":1},{"name":"join-plus","description":"Join multiple lines to a single line.","version":"0.4.0","downloads":1267,"stars":5},{"name":"joker-gaming","description":"Daftar Situs Judi JOKER Gaming Terpercaya Di Indonesia","version":"0.1.0","downloads":0,"stars":1},{"name":"joker-gaming-slot","description":"Link Download Info Terbaik Joker Gaming Slot Lagi Gacor","version":"2.0.0","downloads":0,"stars":0},{"name":"joker-slot","description":"Rekapan Daftar Tutorial Gacor Joker Slot Ter Sensasional","version":"2.0.0","downloads":0,"stars":0},{"name":"joker-slot-123","description":"Ini Daftar Kode Cheat Joker Slot 123 Apk Android","version":"2.0.0","downloads":0,"stars":0},{"name":"joker123","description":"Joker123 merupakan situs slot game online yang menyediakan banyak jenis permainan. Yuk langsung daftar joker123 dan gunakan link alternatifnya!","version":"0.1.0","downloads":0,"stars":0,"theme":"syntax"},{"name":"joker123-gaming-daftar-dan-login","description":"Joker123 Gaming link untuk daftar dan login game joker 388 dan joker 3939","version":"1.1.0","downloads":0,"stars":0,"theme":"ui"},{"name":"joker123-joker388-joker-gaming-situs-judi-slot-online-gacor-via-pulsa","description":"Agen Resmi JOKER GAMING - Link Alternatif & Daftar JOKER123","version":"0.6.0","downloads":0,"stars":0},{"name":"joker123-slot-login","description":"Rekapan Daftar Kode Gacor Joker123 Slot Login Mudah Gratis","version":"2.0.0","downloads":0,"stars":0},{"name":"joker388-terpercaya","version":"2.3.0","downloads":0,"stars":0},{"name":"jonikorpi-atom-solarized-syntax","description":"My implementation of the [Solarized](http://ethanschoonover.com/solarized) Dark color scheme.","version":"0.2.4","downloads":792,"stars":1,"theme":"syntax"},{"name":"jonikorpi-atom-theme-ui","description":"A minimalistic UI theme based on One Dark. Styling loosely based on Light Table (http://lighttable.com). Created by @jonikorpi (https://twitter.com/jonikorpi).","version":"4.4.1","downloads":4646,"stars":7,"theme":"ui"},{"name":"jordanbtucker-apm-test","description":"This is a test package.","version":"3.1.1","downloads":177,"stars":0},{"name":"jorge-word-count","description":"Word count package example","version":"0.1.0","downloads":146,"stars":0},{"name":"jorge2-word-count","description":"A simple test program that counts the words in a page","version":"1.1.0","downloads":38,"stars":0},{"name":"josh-mosh-syntax","version":"2.0.0","downloads":54,"stars":0,"theme":"syntax"},{"name":"jotadeaa-syntax","description":"Dark syntax theme for Atom.","version":"0.3.0","downloads":53,"stars":1,"theme":"syntax"},{"name":"jour-nuit","description":"Like F.lux, for Atom themes. Auto switch UI/Syntax themes depending on the time of the day.","version":"1.0.2","downloads":267,"stars":3},{"name":"journal","description":"A simple journal package. Allows you to create journal entries in a markdown file","version":"0.1.1","downloads":553,"stars":0},{"name":"jovian-night-syntax","description":"Based on my old Sublime text theme","version":"0.3.4","downloads":578,"stars":1,"theme":"syntax"},{"name":"jpcastle-light-syntax","description":"A light syntax theme, inspired Japanese castle and its garden.","version":"0.0.2","downloads":247,"stars":0,"theme":"syntax"},{"name":"jquery","description":"A collection of snippets covering nearly all of the jQuery API.","version":"1.3.0","downloads":74499,"stars":46},{"name":"jquery-snippets","description":"jQuery Snippets for Atom","version":"11.0.0","downloads":132409,"stars":145},{"name":"jquerysc","description":"jQuery Snippets Collection for Atom","version":"0.2.0","downloads":1496,"stars":0},{"name":"js-extractor","version":"0.0.2","downloads":316,"stars":1},{"name":"js-extras","description":"JavaScript extras that either add to or judiciously clobber the Atom defaults.","version":"1.13.0","downloads":1252,"stars":1},{"name":"js-folds","description":"It is a plugin for recording and sharing project folds","version":"1.4.2","downloads":157,"stars":0},{"name":"js-func-viewer","description":"A function structure viewer for Javascript file","version":"1.1.4","downloads":4518,"stars":1},{"name":"js-hyperclick","description":"A hyperclick provider that lets you jump to where variables are defined.","version":"1.19.0","downloads":186979,"stars":216},{"name":"js-hyperclick-config-alternative","description":"A hyperclick provider that lets you jump to where variables are defined.","version":"2.1.0","downloads":211,"stars":0},{"name":"js-hyperclick-project-path","description":"A hyperclick provider that lets you jump to where variables are defined with project path support.","version":"1.12.0","downloads":1073,"stars":0},{"name":"js-hyperx","description":"hyperx syntax highlighting support","version":"1.1.0","downloads":441,"stars":0},{"name":"js-object-notation-converter","description":"Converts between object literal notation and function statement (constructor) notation.","version":"0.1.1","downloads":47,"stars":0},{"name":"js-onsave","description":"Run yui compressor command when you save a javascript file","version":"0.0.2","downloads":919,"stars":2},{"name":"js-patterns-atom-snippets","description":"JavaScript Patterns snippets for Atom","version":"0.2.1","downloads":1784,"stars":8},{"name":"js-refactor","description":"Refactoring support for JavaScript","version":"0.8.1","downloads":35514,"stars":71},{"name":"js-refactor-atom","description":"Javascript refactoring tools to help simplify the process of improving your code","version":"0.10.1","downloads":1409,"stars":1},{"name":"js-test-gen-atom","description":"Js-test-gen-atom generates test templates from your default/named exports.","version":"0.2.0","downloads":3352,"stars":0},{"name":"js-test-toggler","description":"Switch between code and its tests with just a single keyboard shortcut","version":"0.1.1","downloads":52,"stars":0},{"name":"js-to-string","description":"Converts the selected JS lines to string (single-line/concatenated).","version":"1.0.5","downloads":959,"stars":1},{"name":"js2coffee","description":"Convert selected lines or an entire file into coffeescript.","version":"0.19.1","downloads":3308,"stars":15},{"name":"js2ls","description":"Convert selected lines or an entire file into LiveScript.","version":"1.2.0","downloads":176,"stars":0},{"name":"jsartisan-dark-minimalistic-ui","description":"Dark UI Minimalistic Theme","version":"2.4.0","downloads":1411,"stars":0,"theme":"ui"},{"name":"jsb-black-theme","description":"A test theme in development","version":"1.0.4","downloads":0,"stars":2,"theme":"ui"},{"name":"jsb-brown-theme","description":"A test theme in development","version":"1.0.4","downloads":0,"stars":3,"theme":"ui"},{"name":"jsb-orange-theme","description":"A test theme in development","version":"1.0.2","downloads":0,"stars":3,"theme":"ui"},{"name":"jscad-viewer","description":"View jscad files inside Atom.","version":"1.2.0","downloads":769,"stars":3},{"name":"jscs-fixer","description":"Atom package to run jscs --fix on your scripts","version":"1.3.0","downloads":14737,"stars":34},{"name":"jscs-format","downloads":0,"stars":0},{"name":"jscs-snippets","description":"A collection of JSCS snippets for Atom Editor.","version":"0.1.0","downloads":456,"stars":0},{"name":"jsdelivr","description":"Quickly insert any npm package from jsDelivr CDN","version":"1.0.2","downloads":236,"stars":0},{"name":"jsdoc","description":"JSDoc style comments for javascript development","version":"0.9.0","downloads":3756,"stars":34},{"name":"jsdoc-generator","description":"generate html documentation from jsdoc annotation.","version":"0.2.5","downloads":5981,"stars":7},{"name":"jsdoc-preview","description":"Open a rendered version of the JSDoc docstrings in the current editor with `ctrl-shift-d`.","version":"1.2.1","downloads":1907,"stars":1},{"name":"jsfiddle-like-syntax","description":"A color schema with the look of the JsFiddle theme with some tweak","version":"0.2.10","downloads":837,"stars":2,"theme":"syntax"},{"name":"jsfiddle-theme-syntax","description":"Atom syntax theme inspired by JSFiddle Editor.","version":"0.1.2","downloads":493,"stars":0,"theme":"syntax"},{"name":"jsfmt","description":"Format your JavaScript using jsfmt","version":"1.6.0","downloads":1453,"stars":1},{"name":"jsformat","description":"javascript formatting for the atom text editor","version":"0.9.3","downloads":60753,"stars":60},{"name":"jshint","description":"Validate JavaScript with JSHint. In realtime or on save. Supports JSX (React).","version":"1.8.6","downloads":301158,"stars":341},{"name":"jshint-snippets","description":"A collection of JSHint snippets for Atom Editor.","version":"0.2.2","downloads":1424,"stars":5},{"name":"jsl","description":"JSL javascript linter for atom.","version":"0.1.4","downloads":262,"stars":0},{"name":"jslint","description":"JSLint error reports for your Atom editor","version":"1.5.1","downloads":65889,"stars":37},{"name":"jsmidi-atom","description":"JSMidi Atom","version":"0.0.7","downloads":110,"stars":0},{"name":"json-colorer","description":"Color your JSON files","version":"1.0.0","downloads":29554,"stars":15},{"name":"json-converter","description":"Convert csv to json, json to csv, and more.","version":"0.2.4","downloads":24507,"stars":34},{"name":"json-generator","description":"Generate the json dummy data package","version":"0.1.15","downloads":3065,"stars":5},{"name":"json-level-color","description":"Provide customizable colors per level of a JSON object","version":"0.1.4","downloads":4054,"stars":7},{"name":"json-path-finder","description":"json path finder","version":"0.1.9","downloads":6859,"stars":9},{"name":"json-refs","description":"Resolve JSON Reference allows a JSON value to reference another value in a JSON document.","version":"0.1.3","downloads":2590,"stars":2},{"name":"json-schema","description":"Json Schema enhancements for Atom","version":"0.1.15","downloads":43733,"stars":53},{"name":"json-sort","description":"Alphabetically sorts your JSON files, see README.md for how to run","version":"1.6.0","downloads":2700,"stars":6},{"name":"json-to-go-struct","description":"this package helps you convert json to go structs","version":"0.0.5","downloads":4551,"stars":5},{"name":"json-to-html","description":"Mainly for writing json or javascript object on table of markdown.","version":"0.2.4","downloads":6254,"stars":3},{"name":"json-tree","downloads":0,"stars":1},{"name":"jsondb-atom-plugin","description":"A atom plugin which helps in manual editing of Jsondb data files","version":"0.2.0","downloads":115,"stars":1},{"name":"jsonlint","description":"JSON Lint reports for your Atom editor","version":"1.1.4","downloads":35454,"stars":64},{"name":"jsonpp","description":"JSON pretty printer","version":"0.1.1","downloads":4896,"stars":9},{"name":"jspm-dev-buddy","description":"helps by emitting file changed events and makes navigation trivial when error occurs in the browser","version":"0.1.1","downloads":320,"stars":2},{"name":"jspp","downloads":0,"stars":0},{"name":"jss-atom-snippets","description":"JSS snippets for atom","version":"1.5.0","downloads":510,"stars":0},{"name":"jsx-comment","description":"JSX style comments and block comments","version":"0.2.0","downloads":12254,"stars":17},{"name":"jsx-eslint-comment","description":"JSX style comments and block comments","version":"1.0.0","downloads":305,"stars":0},{"name":"jsxbin-encoder","description":"Encodes the selected JSX to JSXBIN.","version":"1.9.11","downloads":753,"stars":0},{"name":"jude","description":"Julia Development Extensions","version":"0.2.9","downloads":4638,"stars":2},{"name":"judi-bola-deposit-via-dana","description":"Kumpulan Situs Judi Bola Online Via Pulsa 10 Ribu Tanpa Potongan","version":"1.19.1","downloads":0,"stars":0},{"name":"judi-bola-deposit-via-ovo","description":"Kumpulan Situs Judi Bola Online Via Pulsa 10 Ribu Tanpa Potongan","version":"1.20.1","downloads":0,"stars":0},{"name":"judi-bola-deposit-via-pulsa","description":"Game Judi Bola Online Deposit Via Pulsa | Agen Live Judi Bola Deposit Pulsa | Daftar Judi Bola Online Deposit Pulsa | Judi Bola Online Via Pulsa Terpercaya","version":"1.20.1","downloads":0,"stars":0},{"name":"judi-bola-gacor-sbobet-24-jam","description":"Daftar Judi bola deposit via dana","version":"1.3.1","downloads":0,"stars":0},{"name":"judi-bola-online-deposit-ovo","description":"Game Judi Bola Online Deposit Via Ovo | Agen Live Judi Bola Deposit Ovo | Daftar Judi Bola Online Deposit Ovo | Judi Bola Online Via Ovo Terpercaya","version":"1.22.0","downloads":0,"stars":0},{"name":"judi-bola-online-deposit-via-dana","description":"Game Judi Bola Online Deposit Via Dana | Agen Live Judi Bola Deposit Dana | Daftar Judi Bola Online Deposit Dana | Judi Bola Online Via Dana Terpercaya","version":"1.21.1","downloads":0,"stars":0},{"name":"judi-bola-online-deposit-via-pulsa","description":"Daftar Situs Bola Online Via Pulsa 10 Ribu | Sbobet Judi Bola Online | Bola Online Terbaik | Link Resmi Bola Online | Bola Online Via Pulsa","version":"1.18.1","downloads":0,"stars":0},{"name":"judi-onlen-slot","description":"Rekomendasi Terbaik Rekomendasi Bo Judi Onlen Slot Gampang Win","version":"2.0.0","downloads":0,"stars":0},{"name":"judi-onlin-slot","description":"Download Apk Cara Main Gacor Judi Onlin Slot Bet Paling Kecil","version":"2.0.0","downloads":0,"stars":0},{"name":"judi-online-slot","description":"Daftar Bo Info Yang Lagi Gacor Judi Online Slot Server Indonesia","version":"2.0.0","downloads":0,"stars":0},{"name":"judi-resmi-slot","description":"Info Jos Gacor Download Apk Demo Judi Resmi Slot Lewat Linkaja","version":"2.0.0","downloads":0,"stars":0},{"name":"judi-slot-deposit-25-rb","description":"Bocoran Situs Judi Slot 25 Rb Gacor Terbaru Dan Paling Terbaik","version":"1.24.1","downloads":0,"stars":0},{"name":"judi-slot-deposit-5-ribu","description":"Link Situs Judi Slot Online Deposit 5 Ribu Tanpa Potongan Terpercaya","version":"1.22.1","downloads":0,"stars":0},{"name":"judi-slot-deposit-via-pulsa-gacor","description":"SLOT88 : Situs Judi Slot Deposit Pulsa Gacor Tanpa Potongan | Situs Slot Depo Via Pulsa Resmi Dan Terlengkap | Slot Deposit Pulsa Gacor Hari Ini Gampang Menang Jackpot","version":"1.17.1","downloads":0,"stars":0},{"name":"judi-slot-deposit-via-qris-5000","description":"Daftar Situs Judi Slot Online Deposit Via QRIS 5000 Tanpa Potongan","version":"1.15.4","downloads":0,"stars":0},{"name":"judi-slot-online-deposit-10-rb","description":"Kumpulan Situs Game Slot Deposit 10 Rb Paling Murah Dan Aman","version":"1.22.2","downloads":0,"stars":0},{"name":"judi-slot-online-deposit-10-ribu","description":"Kumpulan Situs Game Slot Deposit 10 Ribu Paling Murah Dan Aman","version":"1.22.1","downloads":0,"stars":0},{"name":"judi-slot-online-deposit-10000","description":"Daftar Situs Slot Online Deposit 10000 Via Dana Dan Pulsa Mudah Menang Maxwin","version":"1.19.2","downloads":0,"stars":0},{"name":"judi-slot-online-deposit-10rb","description":"Agen Situs Judi Slot Gacor Deposit 10rb 100% Anti Rungkad Resmi","version":"1.21.1","downloads":0,"stars":0},{"name":"judi-slot-online-deposit-10ribu","description":"Link Situs Judi Slot Online Deposit 10ribu Tanpa Potongan Terpercaya","version":"1.20.1","downloads":0,"stars":0},{"name":"judi-slot-online-deposit-20-rb","description":"Bocoran Situs Judi Slot 20 Rb Gacor Terbaru Dan Paling Terbaik","version":"1.23.1","downloads":0,"stars":0},{"name":"judi-slot-online-deposit-20-ribu","description":"Kumpulan Situs Game Slot Deposit 20 Ribu Paling Murah Dan Aman","version":"1.22.2","downloads":0,"stars":0},{"name":"judi-slot-online-deposit-20000","description":"Daftar Situs Slot Online Deposit 20000 Via Dana Dan Pulsa Mudah Menang Maxwin","version":"1.19.3","downloads":0,"stars":0},{"name":"judi-slot-online-deposit-20rb","description":"Agen Situs Judi Slot Gacor Deposit 20rb 200% Anti Rungkad Resmi","version":"1.22.1","downloads":0,"stars":0},{"name":"judi-slot-online-deposit-25-ribu","description":"Kumpulan Situs Game Slot Deposit 25 Ribu Paling Murah Dan Aman","version":"1.23.1","downloads":0,"stars":0},{"name":"judi-slot-online-deposit-25000","description":"Daftar Situs Slot Online Deposit 25000 Via Dana Dan Pulsa Mudah Menang Maxwin","version":"1.20.1","downloads":0,"stars":0},{"name":"judi-slot-online-deposit-25rb","description":"Agen Situs Judi Slot Gacor Deposit 25rb 250% Anti Rungkad Resmi","version":"1.23.1","downloads":0,"stars":0},{"name":"judi-slot-online-deposit-25ribu","description":"Link Situs Judi Slot Online Deposit 25ribu Tanpa Potongan Terpercaya","version":"1.24.1","downloads":0,"stars":0},{"name":"judi-slot-online-deposit-5-rb","description":"Link Situs Judi Slot Online Deposit 5 Rb Tanpa Potongan Terpercaya","version":"1.23.1","downloads":0,"stars":0},{"name":"judi-slot-online-deposit-5000","description":"Daftar Situs Slot Online Deposit 5000 Via Dana Dan Pulsa Mudah Menang Maxwin","version":"1.19.1","downloads":0,"stars":0},{"name":"judi-slot-online-deposit-5rb","description":"Link Situs Judi Slot Online Deposit 5rb Tanpa Potongan Terpercaya","version":"1.21.1","downloads":0,"stars":0},{"name":"judi-slot-online-deposit-5ribu","description":"Link Situs Judi Slot Online Deposit 5ribu Tanpa Potongan Terpercaya","version":"1.20.1","downloads":0,"stars":0},{"name":"judi-slot-pulsa","description":"Ini Daftar Ini Dia Cheat Judi Slot Pulsa New Member 100","version":"2.0.0","downloads":0,"stars":0},{"name":"judi-slot-terbaik","description":"Trik Menang Info Banyak Bonus Judi Slot Terbaik Palling Terpercaya","version":"2.0.0","downloads":0,"stars":0},{"name":"judi-slot-terpercaya","description":"Cara Deposit Daftar Slot Apk Judi Slot Terpercaya Uang Sungguhan","version":"2.0.0","downloads":0,"stars":0},{"name":"juicebox-syntax","description":"A dark syntax theme for Atom. Juicebox features bright, core colors alongside soft, flat-styled elements. This is a syntax theme only, and will not affect the Atom UI (it will work with Light or Dark UI schemes).","version":"1.0.6","downloads":1004,"stars":1,"theme":"syntax"},{"name":"juicy-syntax","description":"A Syntax theme based on juicy sublime theme","version":"1.0.5","downloads":2477,"stars":5,"theme":"syntax"},{"name":"juiz-atom-ui","description":"My favorite UI theme lol","version":"1.1.0","downloads":290,"stars":1,"theme":"ui"},{"name":"julia-client","description":"The core package of Juno, the Julia IDE","version":"0.12.6","downloads":776829,"stars":24},{"name":"jump-lines","description":"Atom package to move the cursor up and down skipping x amount of lines","version":"1.1.0","downloads":320,"stars":1},{"name":"jump-to","description":"Move the cursor or expand the current selection to a position in the current line based on a text search.","version":"0.3.0","downloads":209,"stars":0},{"name":"jump-to-import","description":"Jump to ES6 import/require/bower/npm modules, including Ember.Service and Ember.Component template files. With hyperclick support and project-specific configs.","version":"3.6.5","downloads":6901,"stars":4},{"name":"jump-to-line","description":"Rapidly jump to the start of any line that is currently visible","version":"0.3.0","downloads":371,"stars":1},{"name":"jumpy","description":"An Atom package that creates dynamic hotkeys to jump around files across visible panes.","version":"5.0.2","downloads":67373,"stars":413},{"name":"jumpy-beacon","description":"An Atom package that creates an ocular cue to assist with tab switching","version":"0.2.0","downloads":629,"stars":1},{"name":"juno-plus","description":"Enhances Juno - Julia IDE","version":"0.13.1","downloads":20061,"stars":0},{"name":"jupyter-notebook","description":"Jupyter Notebook, but inside Atom.","version":"0.0.10","downloads":181758,"stars":46},{"name":"jurassic_systems-ui","description":"A purely aesthetic UI theme inspired by Dennis Nedry’s Silicon Graphics IRIX system from the 1993 film 'Jurassic Park.'","version":"0.1.3","downloads":464,"stars":1,"theme":"ui"},{"name":"jurassicsystems-syntax","description":"A syntax theme inspired by Dennis Nedry’s 'Jurassic Systems, System Security Interface Version 4.0.5, Alpha E'","version":"0.1.5","downloads":416,"stars":0,"theme":"syntax"},{"name":"jurassicsystems-ui","downloads":0,"stars":0},{"name":"just-testing-hashtag-no-bugs","description":"Just testing this","version":"0.3.0","downloads":12,"stars":0},{"name":"juttle-viewer","description":"Run juttle and view output in atom.","version":"0.1.2","downloads":65,"stars":0},{"name":"jvpr-dark-syntax","description":"A colorful syntax to work with Python and Javascript languages","version":"1.2.1","downloads":1329,"stars":0,"theme":"syntax"}]